totalrecall/__init__.py
totalrecall/profilers.py
totalrecall/tests/__init__.py
totalrecall/tests/__main__.py
totalrecall/tests/helper.py
totalrecall/tests/test_profiler.py
totalrecall-0.1.1.dist-info/METADATA
totalrecall-0.1.1.dist-info/WHEEL
totalrecall-0.1.1.dist-info/top_level.txt
totalrecall-0.1.1.dist-info/zip-safe
totalrecall-0.1.1.dist-info/RECORD
