Metadata-Version: 2.1
Name: totalrecall
Version: 0.1.1
Summary: A runtime step profiler - for Python.
Home-page: https://github.com/grimen/python-totalrecall
Author: Jonas Grimfelt
Author-email: grimen@gmail.com
License: MIT
Download-URL: https://github.com/grimen/python-totalrecall
Project-URL: repository, https://github.com/grimen/python-totalrecall
Project-URL: bugs, https://github.com/grimen/python-totalrecall/issues
Keywords: profiler,step-profiler,step-runtime-profiler,runtime-profiler,runtime,step,timer,context,function,mixin
Platform: UNKNOWN
Classifier: Topic :: Software Development :: Libraries
Classifier: Development Status :: 5 - Production/Stable
Classifier: Intended Audience :: Developers
Classifier: License :: OSI Approved :: MIT License
Classifier: Operating System :: POSIX
Classifier: Programming Language :: Python
Classifier: Programming Language :: Python :: 2
Classifier: Programming Language :: Python :: 2.7
Classifier: Programming Language :: Python :: 3
Classifier: Programming Language :: Python :: 3.6
Classifier: Programming Language :: Python :: Implementation :: CPython
Classifier: Programming Language :: Python :: Implementation :: PyPy
Requires-Dist: six (>=1.11.0)
Requires-Dist: rootpath (>=0.1.0)
Requires-Dist: mybad (>=0.1.0)
Requires-Dist: mybase (>=0.1.0)
Requires-Dist: inspecta (>=0.1.0)
Requires-Dist: attributedict (>=0.2.0)
Requires-Dist: uuid (>=1.3)
Requires-Dist: colour-runner (>=0.0.5)
Requires-Dist: deepdiff (>=3.3.0)
Requires-Dist: tox (>=3.0.0)
Requires-Dist: coverage (>=4.5.2)
Requires-Dist: codecov (>=2.0.15)
